huaweicloudsdkrgc/__init__.py
huaweicloudsdkrgc/v1/__init__.py
huaweicloudsdkrgc/v1/rgc_async_client.py
huaweicloudsdkrgc/v1/rgc_client.py
huaweicloudsdkrgc/v1/model/__init__.py
huaweicloudsdkrgc/v1/model/access_logging_bucket_baseline.py
huaweicloudsdkrgc/v1/model/account_baseline.py
huaweicloudsdkrgc/v1/model/account_baseline_rsp.py
huaweicloudsdkrgc/v1/model/artifact.py
huaweicloudsdkrgc/v1/model/best_practice_check_item_detail.py
huaweicloudsdkrgc/v1/model/best_practice_overview_item.py
huaweicloudsdkrgc/v1/model/blueprint.py
huaweicloudsdkrgc/v1/model/check_launch_request.py
huaweicloudsdkrgc/v1/model/check_launch_response.py
huaweicloudsdkrgc/v1/model/common_configuration.py
huaweicloudsdkrgc/v1/model/config_rule_compliance.py
huaweicloudsdkrgc/v1/model/content.py
huaweicloudsdkrgc/v1/model/control.py
huaweicloudsdkrgc/v1/model/control_operation.py
huaweicloudsdkrgc/v1/model/control_violation.py
huaweicloudsdkrgc/v1/model/create_account_request.py
huaweicloudsdkrgc/v1/model/create_account_response.py
huaweicloudsdkrgc/v1/model/create_best_practice_detect_request.py
huaweicloudsdkrgc/v1/model/create_best_practice_detect_response.py
huaweicloudsdkrgc/v1/model/create_managed_account_request.py
huaweicloudsdkrgc/v1/model/create_managed_organizational_unit_request.py
huaweicloudsdkrgc/v1/model/create_managed_organizational_unit_response.py
huaweicloudsdkrgc/v1/model/create_organizational_unit.py
huaweicloudsdkrgc/v1/model/create_organizational_unit_req_body.py
huaweicloudsdkrgc/v1/model/create_template_request.py
huaweicloudsdkrgc/v1/model/create_template_request_body.py
huaweicloudsdkrgc/v1/model/create_template_response.py
huaweicloudsdkrgc/v1/model/delete_landing_zone_request.py
huaweicloudsdkrgc/v1/model/delete_landing_zone_response.py
huaweicloudsdkrgc/v1/model/delete_managed_organizational_units_request.py
huaweicloudsdkrgc/v1/model/delete_managed_organizational_units_response.py
huaweicloudsdkrgc/v1/model/delete_template_request.py
huaweicloudsdkrgc-3.1.184.dist-info/METADATA
huaweicloudsdkrgc-3.1.184.dist-info/WHEEL
huaweicloudsdkrgc-3.1.184.dist-info/licenses/LICENSE
huaweicloudsdkrgc-3.1.184.dist-info/RECORD
